{
  "routes": [
    {
      "method": "GET",
      "path": "/query/features",
      "handler": "query.features",
      "config": {
        "policies": []
      }
    },
    {
      "method": "POST",
      "path": "/query/features",
      "handler": "query.features",
      "config": {
        "policies": []
      }
    },
    {
      "method": "POST",
      "path": "/query/timeline",
      "handler": "query.timeline",
      "config": {
        "policies": []
      }
    },
    {
      "method": "GET",
      "path": "/query/concepts",
      "handler": "query.concepts",
      "config": {
        "policies": []
      }
    },
    {
      "method": "POST",
      "path": "/query/concepts",
      "handler": "query.concepts",
      "config": {
        "policies": []
      }
    },
    {
      "method": "POST",
      "path": "/query/results",
      "handler": "query.results",
      "config": {
        "policies": []
      }
    }
  ]
}
